[
  {
    "a": 2.53, 
    "om": 87.4973, 
    "e": 0.657, 
    "i": 4.92, 
    "q": 0.86758, 
    "w": 230.8
  }, 
  {
    "a": 2.84, 
    "om": 89.1487, 
    "e": 0.6952, 
    "i": 5.17, 
    "q": 0.8664, 
    "w": 230.13
  }, 
  {
    "a": 2.6, 
    "om": 88.4226, 
    "e": 0.6647, 
    "i": 5.33, 
    "q": 0.8722, 
    "w": 229.81
  }, 
  {
    "a": 2.41, 
    "om": 91.2871, 
    "e": 0.6341, 
    "i": 4.99, 
    "q": 0.88248, 
    "w": 228.61
  }, 
  {
    "a": 2.55, 
    "om": 90.4943, 
    "e": 0.6526, 
    "i": 4.53, 
    "q": 0.88549, 
    "w": 227.57
  }, 
  {
    "a": 2.28, 
    "om": 89.4707, 
    "e": 0.6137, 
    "i": 4.24, 
    "q": 0.88072, 
    "w": 229.46
  }, 
  {
    "a": 2.53, 
    "om": 89.1355, 
    "e": 0.6563, 
    "i": 4.71, 
    "q": 0.8704, 
    "w": 230.32
  }, 
  {
    "a": 2.54, 
    "om": 89.4367, 
    "e": 0.6512, 
    "i": 4.27, 
    "q": 0.88586, 
    "w": 227.52
  }, 
  {
    "a": 2.54, 
    "om": 88.6372, 
    "e": 0.6577, 
    "i": 5.16, 
    "q": 0.87097, 
    "w": 230.18
  }, 
  {
    "a": 2.53, 
    "om": 87.3218, 
    "e": 0.6603, 
    "i": 4.73, 
    "q": 0.85834, 
    "w": 232.39
  }, 
  {
    "a": 2.66, 
    "om": 91.3013, 
    "e": 0.6693, 
    "i": 5.02, 
    "q": 0.87796, 
    "w": 228.63
  }, 
  {
    "a": 2.05, 
    "om": 88.5068, 
    "e": 0.5689, 
    "i": 4.47, 
    "q": 0.88417, 
    "w": 230.03
  }, 
  {
    "a": 2.65, 
    "om": 91.0618, 
    "e": 0.6667, 
    "i": 4.86, 
    "q": 0.88307, 
    "w": 227.73
  }, 
  {
    "a": 2.83, 
    "om": 92.9663, 
    "e": 0.6936, 
    "i": 4.82, 
    "q": 0.86757, 
    "w": 229.99
  }, 
  {
    "a": 2.64, 
    "om": 90.6002, 
    "e": 0.6651, 
    "i": 4.73, 
    "q": 0.88417, 
    "w": 227.54
  }, 
  {
    "a": 2.53, 
    "om": 86.7882, 
    "e": 0.6633, 
    "i": 4.83, 
    "q": 0.85209, 
    "w": 233.41
  }, 
  {
    "a": 2.54, 
    "om": 94.4635, 
    "e": 0.6555, 
    "i": 5.76, 
    "q": 0.8741, 
    "w": 229.74
  }, 
  {
    "a": 2.55, 
    "om": 91.5574, 
    "e": 0.6532, 
    "i": 5.41, 
    "q": 0.88509, 
    "w": 227.69
  }, 
  {
    "a": 2.15, 
    "om": 90.6894, 
    "e": 0.5878, 
    "i": 5.33, 
    "q": 0.88481, 
    "w": 229.38
  }, 
  {
    "a": 2.27, 
    "om": 90.8219, 
    "e": 0.6059, 
    "i": 4.92, 
    "q": 0.8964, 
    "w": 226.54
  }, 
  {
    "a": 2.24, 
    "om": 90.771, 
    "e": 0.6051, 
    "i": 5.24, 
    "q": 0.88457, 
    "w": 228.94
  }, 
  {
    "a": 2.65, 
    "om": 91.3011, 
    "e": 0.6685, 
    "i": 4.38, 
    "q": 0.87849, 
    "w": 228.54
  }, 
  {
    "a": 2.43, 
    "om": 90.0827, 
    "e": 0.6356, 
    "i": 4.62, 
    "q": 0.88499, 
    "w": 228.07
  }, 
  {
    "a": 2.76, 
    "om": 89.465, 
    "e": 0.6853, 
    "i": 4.25, 
    "q": 0.86958, 
    "w": 229.77
  }
]