[
  {
    "a": 67.41, 
    "om": 333.8021, 
    "e": 0.9891, 
    "i": 121.7, 
    "q": 0.73792, 
    "w": 240.73
  }, 
  {
    "a": 5.94, 
    "om": 323.8419, 
    "e": 0.886, 
    "i": 121.38, 
    "q": 0.67711, 
    "w": 250.66
  }, 
  {
    "a": 4.6, 
    "om": 327.0794, 
    "e": 0.8319, 
    "i": 127.28, 
    "q": 0.77318, 
    "w": 238.57
  }, 
  {
    "a": 3.68, 
    "om": 331.5418, 
    "e": 0.7868, 
    "i": 125.18, 
    "q": 0.78452, 
    "w": 237.94
  }, 
  {
    "a": 7.68, 
    "om": 332.93, 
    "e": 0.8942, 
    "i": 125.72, 
    "q": 0.813, 
    "w": 231.48
  }, 
  {
    "a": 8.62, 
    "om": 332.4591, 
    "e": 0.9067, 
    "i": 132.8, 
    "q": 0.80396, 
    "w": 232.66
  }, 
  {
    "a": 7.65, 
    "om": 329.8944, 
    "e": 0.9048, 
    "i": 122.61, 
    "q": 0.72802, 
    "w": 243.56
  }, 
  {
    "a": 5.13, 
    "om": 334.0107, 
    "e": 0.8496, 
    "i": 128.31, 
    "q": 0.77222, 
    "w": 238.52
  }, 
  {
    "a": 7.92, 
    "om": 329.1852, 
    "e": 0.9066, 
    "i": 124.99, 
    "q": 0.73962, 
    "w": 241.92
  }, 
  {
    "a": 29.34, 
    "om": 332.3414, 
    "e": 0.9734, 
    "i": 132.32, 
    "q": 0.78088, 
    "w": 235.01
  }, 
  {
    "a": 44.98, 
    "om": 331.9306, 
    "e": 0.9824, 
    "i": 119.52, 
    "q": 0.79374, 
    "w": 233.0
  }, 
  {
    "a": 10.3, 
    "om": 327.2623, 
    "e": 0.9337, 
    "i": 126.94, 
    "q": 0.68323, 
    "w": 248.82
  }, 
  {
    "a": 12.08, 
    "om": 326.89, 
    "e": 0.9391, 
    "i": 123.0, 
    "q": 0.73615, 
    "w": 241.71
  }, 
  {
    "a": 7.99, 
    "om": 329.8138, 
    "e": 0.9154, 
    "i": 124.29, 
    "q": 0.67587, 
    "w": 250.23
  }, 
  {
    "a": 7.39, 
    "om": 326.5835, 
    "e": 0.9081, 
    "i": 120.21, 
    "q": 0.67946, 
    "w": 249.87
  }, 
  {
    "a": 13.89, 
    "om": 334.5659, 
    "e": 0.9454, 
    "i": 115.75, 
    "q": 0.75929, 
    "w": 238.58
  }, 
  {
    "a": 18.62, 
    "om": 334.5346, 
    "e": 0.9572, 
    "i": 123.32, 
    "q": 0.79668, 
    "w": 233.02
  }, 
  {
    "a": 20.05, 
    "om": 322.1445, 
    "e": 0.9643, 
    "i": 122.19, 
    "q": 0.71551, 
    "w": 243.91
  }, 
  {
    "a": 14.36, 
    "om": 332.2525, 
    "e": 0.9491, 
    "i": 119.09, 
    "q": 0.73109, 
    "w": 242.32
  }, 
  {
    "a": 17.71, 
    "om": 332.86, 
    "e": 0.9623, 
    "i": 125.3, 
    "q": 0.66732, 
    "w": 250.33
  }, 
  {
    "a": 5.12, 
    "om": 324.77, 
    "e": 0.8622, 
    "i": 122.93, 
    "q": 0.70479, 
    "w": 247.56
  }, 
  {
    "a": 11.31, 
    "om": 329.798, 
    "e": 0.9331, 
    "i": 122.1, 
    "q": 0.75657, 
    "w": 239.07
  }, 
  {
    "a": 5.73, 
    "om": 327.3008, 
    "e": 0.8635, 
    "i": 127.89, 
    "q": 0.78136, 
    "w": 236.72
  }, 
  {
    "a": 7.63, 
    "om": 328.788, 
    "e": 0.898, 
    "i": 127.4, 
    "q": 0.77795, 
    "w": 236.62
  }, 
  {
    "a": 11.13, 
    "om": 332.251, 
    "e": 0.939, 
    "i": 127.35, 
    "q": 0.67855, 
    "w": 249.4
  }, 
  {
    "a": 26.65, 
    "om": 332.0306, 
    "e": 0.9712, 
    "i": 120.76, 
    "q": 0.76773, 
    "w": 236.9
  }, 
  {
    "a": 15.98, 
    "om": 326.9923, 
    "e": 0.9548, 
    "i": 121.42, 
    "q": 0.72207, 
    "w": 243.31
  }, 
  {
    "a": 10.97, 
    "om": 330.3104, 
    "e": 0.9276, 
    "i": 127.6, 
    "q": 0.79432, 
    "w": 233.72
  }
]