[
  {
    "a": 29.06, 
    "om": 302.558, 
    "e": 0.9815, 
    "i": 81.61, 
    "q": 0.53625, 
    "w": 265.35
  }, 
  {
    "a": 40.07, 
    "om": 300.3445, 
    "e": 0.9863, 
    "i": 78.89, 
    "q": 0.54967, 
    "w": 263.63
  }, 
  {
    "a": 30.45, 
    "om": 305.7292, 
    "e": 0.9826, 
    "i": 81.4, 
    "q": 0.52837, 
    "w": 266.27
  }, 
  {
    "a": 16.18, 
    "om": 302.9146, 
    "e": 0.9658, 
    "i": 82.23, 
    "q": 0.55391, 
    "w": 263.69
  }, 
  {
    "a": 7.43, 
    "om": 309.1444, 
    "e": 0.9337, 
    "i": 84.71, 
    "q": 0.49248, 
    "w": 272.03
  }, 
  {
    "a": 9.92, 
    "om": 305.7936, 
    "e": 0.9437, 
    "i": 85.35, 
    "q": 0.55893, 
    "w": 263.71
  }, 
  {
    "a": 6.77, 
    "om": 307.0954, 
    "e": 0.926, 
    "i": 82.88, 
    "q": 0.50127, 
    "w": 271.22
  }, 
  {
    "a": 17.27, 
    "om": 305.9993, 
    "e": 0.9683, 
    "i": 81.46, 
    "q": 0.54802, 
    "w": 264.34
  }, 
  {
    "a": 8.75, 
    "om": 301.0967, 
    "e": 0.9399, 
    "i": 85.6, 
    "q": 0.52561, 
    "w": 267.8
  }, 
  {
    "a": 15.96, 
    "om": 307.6062, 
    "e": 0.964, 
    "i": 76.38, 
    "q": 0.57401, 
    "w": 261.37
  }, 
  {
    "a": 14.04, 
    "om": 302.9612, 
    "e": 0.9589, 
    "i": 77.09, 
    "q": 0.57721, 
    "w": 261.08
  }, 
  {
    "a": 5.04, 
    "om": 302.5292, 
    "e": 0.8897, 
    "i": 80.99, 
    "q": 0.55563, 
    "w": 265.7
  }, 
  {
    "a": 22.49, 
    "om": 301.2079, 
    "e": 0.9765, 
    "i": 81.86, 
    "q": 0.52849, 
    "w": 266.39
  }, 
  {
    "a": 18.49, 
    "om": 303.0035, 
    "e": 0.9695, 
    "i": 81.99, 
    "q": 0.56377, 
    "w": 262.41
  }, 
  {
    "a": 8.7, 
    "om": 300.0867, 
    "e": 0.9438, 
    "i": 84.02, 
    "q": 0.48882, 
    "w": 272.09
  }
]