[
  {
    "a": 7.493, 
    "om": 62.988, 
    "e": 0.964, 
    "i": 132.65, 
    "q": 0.2672, 
    "w": 119.04
  }, 
  {
    "a": 6.184, 
    "om": 63.001, 
    "e": 0.952, 
    "i": 128.42, 
    "q": 0.295, 
    "w": 115.94
  }, 
  {
    "a": 20.344, 
    "om": 63.016, 
    "e": 0.986, 
    "i": 131.71, 
    "q": 0.2805, 
    "w": 116.22
  }, 
  {
    "a": 5.855, 
    "om": 8.702, 
    "e": 0.831, 
    "i": 172.51, 
    "q": 0.9914, 
    "w": 348.19
  }, 
  {
    "a": 9.209, 
    "om": 13.712, 
    "e": 0.894, 
    "i": 173.27, 
    "q": 0.974, 
    "w": 341.09
  }, 
  {
    "a": 9.969, 
    "om": 63.549, 
    "e": 0.969, 
    "i": 133.18, 
    "q": 0.3091, 
    "w": 113.3
  }, 
  {
    "a": 29.486, 
    "om": 63.603, 
    "e": 0.99, 
    "i": 132.82, 
    "q": 0.3033, 
    "w": 113.12
  }, 
  {
    "a": 11.3, 
    "om": 63.693, 
    "e": 0.972, 
    "i": 133.29, 
    "q": 0.3156, 
    "w": 112.33
  }, 
  {
    "a": 5.318, 
    "om": 63.693, 
    "e": 0.947, 
    "i": 131.42, 
    "q": 0.2817, 
    "w": 117.98
  }, 
  {
    "a": 21.038, 
    "om": 64.596, 
    "e": 0.987, 
    "i": 133.24, 
    "q": 0.2784, 
    "w": 116.45
  }, 
  {
    "a": 49.897, 
    "om": 64.811, 
    "e": 0.994, 
    "i": 132.72, 
    "q": 0.2982, 
    "w": 113.57
  }, 
  {
    "a": 8.89, 
    "om": 66.598, 
    "e": 0.973, 
    "i": 134.36, 
    "q": 0.2444, 
    "w": 121.72
  }, 
  {
    "a": 10.649, 
    "om": 66.701, 
    "e": 0.977, 
    "i": 130.31, 
    "q": 0.2469, 
    "w": 121.15
  }, 
  {
    "a": 12.592, 
    "om": 66.704, 
    "e": 0.978, 
    "i": 123.18, 
    "q": 0.2768, 
    "w": 117.07
  }, 
  {
    "a": 15.691, 
    "om": 67.502, 
    "e": 0.982, 
    "i": 131.48, 
    "q": 0.2787, 
    "w": 116.61
  }, 
  {
    "a": 4.799, 
    "om": 67.629, 
    "e": 0.942, 
    "i": 135.69, 
    "q": 0.2768, 
    "w": 118.86
  }, 
  {
    "a": 6.107, 
    "om": 67.666, 
    "e": 0.958, 
    "i": 133.38, 
    "q": 0.2567, 
    "w": 120.8
  }, 
  {
    "a": 36.585, 
    "om": 67.695, 
    "e": 0.993, 
    "i": 130.09, 
    "q": 0.2657, 
    "w": 117.81
  }, 
  {
    "a": 3.886, 
    "om": 67.736, 
    "e": 0.93, 
    "i": 126.11, 
    "q": 0.2721, 
    "w": 120.18
  }, 
  {
    "a": 18.162, 
    "om": 67.763, 
    "e": 0.985, 
    "i": 129.61, 
    "q": 0.2657, 
    "w": 118.17
  }, 
  {
    "a": 18.307, 
    "om": 67.767, 
    "e": 0.986, 
    "i": 130.21, 
    "q": 0.2608, 
    "w": 118.81
  }, 
  {
    "a": 23.868, 
    "om": 67.785, 
    "e": 0.989, 
    "i": 129.9, 
    "q": 0.2728, 
    "w": 117.07
  }, 
  {
    "a": 14.486, 
    "om": 67.841, 
    "e": 0.983, 
    "i": 129.75, 
    "q": 0.2534, 
    "w": 119.96
  }, 
  {
    "a": 12.79, 
    "om": 68.591, 
    "e": 0.98, 
    "i": 130.74, 
    "q": 0.2569, 
    "w": 119.61
  }, 
  {
    "a": 18.309, 
    "om": 68.604, 
    "e": 0.985, 
    "i": 128.28, 
    "q": 0.2789, 
    "w": 116.45
  }, 
  {
    "a": 56.881, 
    "om": 68.675, 
    "e": 0.995, 
    "i": 130.64, 
    "q": 0.2614, 
    "w": 118.24
  }, 
  {
    "a": 10.868, 
    "om": 68.711, 
    "e": 0.975, 
    "i": 137.29, 
    "q": 0.2692, 
    "w": 118.2
  }, 
  {
    "a": 14.317, 
    "om": 68.728, 
    "e": 0.98, 
    "i": 129.96, 
    "q": 0.292, 
    "w": 114.99
  }, 
  {
    "a": 12.196, 
    "om": 68.733, 
    "e": 0.977, 
    "i": 132.3, 
    "q": 0.2789, 
    "w": 116.81
  }, 
  {
    "a": 30.291, 
    "om": 68.776, 
    "e": 0.992, 
    "i": 125.19, 
    "q": 0.2386, 
    "w": 121.47
  }, 
  {
    "a": 10.174, 
    "om": 68.846, 
    "e": 0.97, 
    "i": 129.1, 
    "q": 0.3076, 
    "w": 113.43
  }, 
  {
    "a": 44.56, 
    "om": 68.873, 
    "e": 0.994, 
    "i": 130.66, 
    "q": 0.2572, 
    "w": 118.86
  }, 
  {
    "a": 11.689, 
    "om": 69.501, 
    "e": 0.978, 
    "i": 129.39, 
    "q": 0.2545, 
    "w": 120.02
  }, 
  {
    "a": 19.447, 
    "om": 69.515, 
    "e": 0.986, 
    "i": 130.45, 
    "q": 0.2646, 
    "w": 118.26
  }, 
  {
    "a": 55.112, 
    "om": 69.625, 
    "e": 0.995, 
    "i": 130.07, 
    "q": 0.2677, 
    "w": 117.43
  }, 
  {
    "a": 17.374, 
    "om": 69.668, 
    "e": 0.984, 
    "i": 131.63, 
    "q": 0.2755, 
    "w": 116.92
  }, 
  {
    "a": 6.834, 
    "om": 69.677, 
    "e": 0.958, 
    "i": 132.83, 
    "q": 0.2895, 
    "w": 116.36
  }, 
  {
    "a": 20.95, 
    "om": 69.729, 
    "e": 0.987, 
    "i": 131.04, 
    "q": 0.268, 
    "w": 117.76
  }, 
  {
    "a": 7.384, 
    "om": 69.738, 
    "e": 0.965, 
    "i": 129.35, 
    "q": 0.2617, 
    "w": 119.75
  }, 
  {
    "a": 9.658, 
    "om": 69.81, 
    "e": 0.962, 
    "i": 133.76, 
    "q": 0.3643, 
    "w": 106.61
  }, 
  {
    "a": 41.011, 
    "om": 69.814, 
    "e": 0.993, 
    "i": 130.41, 
    "q": 0.2708, 
    "w": 117.09
  }, 
  {
    "a": 8.252, 
    "om": 69.823, 
    "e": 0.968, 
    "i": 129.01, 
    "q": 0.261, 
    "w": 119.64
  }, 
  {
    "a": 14.03, 
    "om": 69.84, 
    "e": 0.98, 
    "i": 133.98, 
    "q": 0.2805, 
    "w": 116.46
  }, 
  {
    "a": 25.017, 
    "om": 69.873, 
    "e": 0.988, 
    "i": 131.73, 
    "q": 0.2897, 
    "w": 114.87
  }, 
  {
    "a": 19.037, 
    "om": 69.881, 
    "e": 0.985, 
    "i": 131.02, 
    "q": 0.2916, 
    "w": 114.8
  }, 
  {
    "a": 22.795, 
    "om": 70.651, 
    "e": 0.988, 
    "i": 130.26, 
    "q": 0.267, 
    "w": 117.84
  }, 
  {
    "a": 43.004, 
    "om": 70.662, 
    "e": 0.993, 
    "i": 131.28, 
    "q": 0.3149, 
    "w": 111.48
  }, 
  {
    "a": 8.1, 
    "om": 70.687, 
    "e": 0.967, 
    "i": 129.5, 
    "q": 0.2637, 
    "w": 119.31
  }, 
  {
    "a": 12.853, 
    "om": 70.699, 
    "e": 0.973, 
    "i": 132.54, 
    "q": 0.3436, 
    "w": 108.71
  }, 
  {
    "a": 23.63, 
    "om": 70.742, 
    "e": 0.988, 
    "i": 132.86, 
    "q": 0.2964, 
    "w": 114.05
  }, 
  {
    "a": 20.813, 
    "om": 70.751, 
    "e": 0.988, 
    "i": 129.36, 
    "q": 0.2578, 
    "w": 119.09
  }, 
  {
    "a": 18.928, 
    "om": 70.755, 
    "e": 0.986, 
    "i": 131.01, 
    "q": 0.2649, 
    "w": 118.22
  }, 
  {
    "a": 12.616, 
    "om": 70.77, 
    "e": 0.978, 
    "i": 131.74, 
    "q": 0.2795, 
    "w": 116.69
  }, 
  {
    "a": 8.806, 
    "om": 70.779, 
    "e": 0.958, 
    "i": 128.08, 
    "q": 0.3691, 
    "w": 106.18
  }, 
  {
    "a": 19.895, 
    "om": 70.814, 
    "e": 0.988, 
    "i": 130.21, 
    "q": 0.2492, 
    "w": 120.26
  }, 
  {
    "a": 16.918, 
    "om": 70.822, 
    "e": 0.984, 
    "i": 131.53, 
    "q": 0.2671, 
    "w": 118.02
  }, 
  {
    "a": 3.82, 
    "om": 70.83, 
    "e": 0.902, 
    "i": 129.91, 
    "q": 0.373, 
    "w": 108.09
  }, 
  {
    "a": 6.049, 
    "om": 70.83, 
    "e": 0.955, 
    "i": 125.69, 
    "q": 0.2751, 
    "w": 118.44
  }, 
  {
    "a": 6.758, 
    "om": 70.856, 
    "e": 0.956, 
    "i": 132.19, 
    "q": 0.2937, 
    "w": 115.86
  }, 
  {
    "a": 29.195, 
    "om": 71.547, 
    "e": 0.992, 
    "i": 129.39, 
    "q": 0.2462, 
    "w": 120.46
  }, 
  {
    "a": 10.975, 
    "om": 71.595, 
    "e": 0.975, 
    "i": 129.96, 
    "q": 0.2688, 
    "w": 118.22
  }, 
  {
    "a": 104.783, 
    "om": 71.6, 
    "e": 0.998, 
    "i": 127.56, 
    "q": 0.2603, 
    "w": 118.27
  }, 
  {
    "a": 17.508, 
    "om": 71.605, 
    "e": 0.982, 
    "i": 134.7, 
    "q": 0.3149, 
    "w": 111.93
  }, 
  {
    "a": 56.88, 
    "om": 71.605, 
    "e": 0.996, 
    "i": 129.16, 
    "q": 0.2411, 
    "w": 120.93
  }, 
  {
    "a": 22.995, 
    "om": 71.67, 
    "e": 0.987, 
    "i": 130.45, 
    "q": 0.3093, 
    "w": 112.44
  }, 
  {
    "a": 9.827, 
    "om": 71.681, 
    "e": 0.975, 
    "i": 131.21, 
    "q": 0.2481, 
    "w": 121.07
  }, 
  {
    "a": 12.967, 
    "om": 71.683, 
    "e": 0.976, 
    "i": 125.44, 
    "q": 0.3133, 
    "w": 112.4
  }, 
  {
    "a": 17.955, 
    "om": 71.711, 
    "e": 0.987, 
    "i": 128.19, 
    "q": 0.2405, 
    "w": 121.49
  }, 
  {
    "a": 15.073, 
    "om": 71.714, 
    "e": 0.979, 
    "i": 126.54, 
    "q": 0.3229, 
    "w": 111.07
  }, 
  {
    "a": 13.451, 
    "om": 71.742, 
    "e": 0.98, 
    "i": 129.98, 
    "q": 0.2734, 
    "w": 117.39
  }, 
  {
    "a": 8.362, 
    "om": 71.757, 
    "e": 0.969, 
    "i": 129.03, 
    "q": 0.2595, 
    "w": 119.81
  }, 
  {
    "a": 6.713, 
    "om": 71.77, 
    "e": 0.958, 
    "i": 129.89, 
    "q": 0.283, 
    "w": 117.2
  }, 
  {
    "a": 11.27, 
    "om": 71.781, 
    "e": 0.975, 
    "i": 135.44, 
    "q": 0.2808, 
    "w": 116.64
  }, 
  {
    "a": 12.829, 
    "om": 71.781, 
    "e": 0.979, 
    "i": 130.45, 
    "q": 0.2678, 
    "w": 118.18
  }, 
  {
    "a": 18.976, 
    "om": 71.823, 
    "e": 0.985, 
    "i": 128.54, 
    "q": 0.2789, 
    "w": 116.41
  }, 
  {
    "a": 4.507, 
    "om": 71.837, 
    "e": 0.943, 
    "i": 128.46, 
    "q": 0.256, 
    "w": 121.68
  }, 
  {
    "a": 19.598, 
    "om": 71.848, 
    "e": 0.987, 
    "i": 130.45, 
    "q": 0.262, 
    "w": 118.57
  }, 
  {
    "a": 7.434, 
    "om": 71.849, 
    "e": 0.968, 
    "i": 128.19, 
    "q": 0.2409, 
    "w": 122.44
  }, 
  {
    "a": 7.755, 
    "om": 71.866, 
    "e": 0.968, 
    "i": 128.44, 
    "q": 0.2474, 
    "w": 121.5
  }, 
  {
    "a": 9.46, 
    "om": 72.66, 
    "e": 0.975, 
    "i": 128.73, 
    "q": 0.2373, 
    "w": 122.55
  }, 
  {
    "a": 22.838, 
    "om": 72.678, 
    "e": 0.988, 
    "i": 129.7, 
    "q": 0.2656, 
    "w": 118.0
  }, 
  {
    "a": 20.346, 
    "om": 72.697, 
    "e": 0.988, 
    "i": 125.73, 
    "q": 0.2432, 
    "w": 121.04
  }, 
  {
    "a": 509.675, 
    "om": 72.698, 
    "e": 0.999, 
    "i": 131.6, 
    "q": 0.294, 
    "w": 113.81
  }, 
  {
    "a": 5.031, 
    "om": 72.698, 
    "e": 0.941, 
    "i": 131.87, 
    "q": 0.2981, 
    "w": 116.04
  }, 
  {
    "a": 15.342, 
    "om": 72.699, 
    "e": 0.983, 
    "i": 128.69, 
    "q": 0.2624, 
    "w": 118.7
  }, 
  {
    "a": 7.864, 
    "om": 72.724, 
    "e": 0.969, 
    "i": 127.79, 
    "q": 0.2406, 
    "w": 122.39
  }, 
  {
    "a": 5.549, 
    "om": 72.725, 
    "e": 0.955, 
    "i": 127.62, 
    "q": 0.2503, 
    "w": 121.82
  }, 
  {
    "a": 9.35, 
    "om": 72.725, 
    "e": 0.974, 
    "i": 130.37, 
    "q": 0.247, 
    "w": 121.26
  }, 
  {
    "a": 5.062, 
    "om": 72.727, 
    "e": 0.949, 
    "i": 126.18, 
    "q": 0.2591, 
    "w": 120.93
  }, 
  {
    "a": 12.618, 
    "om": 72.775, 
    "e": 0.98, 
    "i": 131.38, 
    "q": 0.2563, 
    "w": 119.68
  }, 
  {
    "a": 8.129, 
    "om": 72.784, 
    "e": 0.971, 
    "i": 128.32, 
    "q": 0.2345, 
    "w": 123.14
  }, 
  {
    "a": 26.167, 
    "om": 72.791, 
    "e": 0.988, 
    "i": 122.22, 
    "q": 0.3242, 
    "w": 110.52
  }, 
  {
    "a": 14.692, 
    "om": 72.802, 
    "e": 0.984, 
    "i": 127.54, 
    "q": 0.2397, 
    "w": 121.75
  }, 
  {
    "a": 7.54, 
    "om": 72.81, 
    "e": 0.967, 
    "i": 122.97, 
    "q": 0.2496, 
    "w": 121.26
  }, 
  {
    "a": 32.577, 
    "om": 72.826, 
    "e": 0.992, 
    "i": 132.03, 
    "q": 0.2585, 
    "w": 118.77
  }, 
  {
    "a": 60.996, 
    "om": 72.848, 
    "e": 0.996, 
    "i": 128.16, 
    "q": 0.2607, 
    "w": 118.29
  }, 
  {
    "a": 8.3, 
    "om": 72.876, 
    "e": 0.969, 
    "i": 130.58, 
    "q": 0.2577, 
    "w": 120.05
  }, 
  {
    "a": 30.175, 
    "om": 72.879, 
    "e": 0.991, 
    "i": 129.4, 
    "q": 0.259, 
    "w": 118.73
  }, 
  {
    "a": 21.947, 
    "om": 72.886, 
    "e": 0.989, 
    "i": 129.17, 
    "q": 0.2392, 
    "w": 121.52
  }, 
  {
    "a": 9.422, 
    "om": 72.89, 
    "e": 0.973, 
    "i": 129.29, 
    "q": 0.2518, 
    "w": 120.62
  }, 
  {
    "a": 33.783, 
    "om": 72.89, 
    "e": 0.992, 
    "i": 128.01, 
    "q": 0.2638, 
    "w": 118.06
  }, 
  {
    "a": 15.004, 
    "om": 72.9, 
    "e": 0.979, 
    "i": 131.07, 
    "q": 0.3174, 
    "w": 111.75
  }, 
  {
    "a": 56.264, 
    "om": 73.643, 
    "e": 0.996, 
    "i": 128.33, 
    "q": 0.2499, 
    "w": 119.75
  }, 
  {
    "a": 10.55, 
    "om": 73.66, 
    "e": 0.976, 
    "i": 126.96, 
    "q": 0.249, 
    "w": 120.85
  }, 
  {
    "a": 9.251, 
    "om": 73.683, 
    "e": 0.97, 
    "i": 126.21, 
    "q": 0.2731, 
    "w": 117.89
  }, 
  {
    "a": 12.99, 
    "om": 73.686, 
    "e": 0.981, 
    "i": 128.11, 
    "q": 0.2489, 
    "w": 120.62
  }, 
  {
    "a": 5.427, 
    "om": 73.729, 
    "e": 0.958, 
    "i": 129.32, 
    "q": 0.2301, 
    "w": 124.53
  }, 
  {
    "a": 5.524, 
    "om": 73.736, 
    "e": 0.958, 
    "i": 128.35, 
    "q": 0.2341, 
    "w": 123.96
  }, 
  {
    "a": 5.609, 
    "om": 73.738, 
    "e": 0.939, 
    "i": 128.49, 
    "q": 0.341, 
    "w": 110.5
  }, 
  {
    "a": 12.348, 
    "om": 73.752, 
    "e": 0.98, 
    "i": 128.15, 
    "q": 0.2453, 
    "w": 121.16
  }, 
  {
    "a": 18.371, 
    "om": 73.771, 
    "e": 0.987, 
    "i": 133.47, 
    "q": 0.2354, 
    "w": 122.15
  }, 
  {
    "a": 13.604, 
    "om": 73.786, 
    "e": 0.976, 
    "i": 127.11, 
    "q": 0.3255, 
    "w": 110.84
  }, 
  {
    "a": 32.706, 
    "om": 73.787, 
    "e": 0.992, 
    "i": 129.79, 
    "q": 0.2634, 
    "w": 118.11
  }, 
  {
    "a": 11.613, 
    "om": 73.797, 
    "e": 0.979, 
    "i": 127.89, 
    "q": 0.2474, 
    "w": 120.93
  }, 
  {
    "a": 59.093, 
    "om": 73.801, 
    "e": 0.995, 
    "i": 130.49, 
    "q": 0.2804, 
    "w": 115.74
  }, 
  {
    "a": 5.961, 
    "om": 73.806, 
    "e": 0.948, 
    "i": 128.54, 
    "q": 0.3119, 
    "w": 113.87
  }, 
  {
    "a": 12.752, 
    "om": 73.812, 
    "e": 0.977, 
    "i": 129.65, 
    "q": 0.2982, 
    "w": 114.3
  }, 
  {
    "a": 10.399, 
    "om": 73.819, 
    "e": 0.977, 
    "i": 127.57, 
    "q": 0.2432, 
    "w": 121.62
  }, 
  {
    "a": 8.941, 
    "om": 73.841, 
    "e": 0.97, 
    "i": 127.12, 
    "q": 0.2666, 
    "w": 118.78
  }, 
  {
    "a": 7.107, 
    "om": 73.846, 
    "e": 0.965, 
    "i": 133.93, 
    "q": 0.2462, 
    "w": 121.81
  }, 
  {
    "a": 71.118, 
    "om": 73.857, 
    "e": 0.996, 
    "i": 130.92, 
    "q": 0.2614, 
    "w": 118.17
  }, 
  {
    "a": 8.999, 
    "om": 73.859, 
    "e": 0.973, 
    "i": 127.79, 
    "q": 0.2463, 
    "w": 121.42
  }, 
  {
    "a": 11.033, 
    "om": 73.865, 
    "e": 0.975, 
    "i": 128.7, 
    "q": 0.2698, 
    "w": 118.07
  }, 
  {
    "a": 18.314, 
    "om": 73.873, 
    "e": 0.987, 
    "i": 128.92, 
    "q": 0.2435, 
    "w": 121.05
  }, 
  {
    "a": 11.988, 
    "om": 73.884, 
    "e": 0.978, 
    "i": 139.18, 
    "q": 0.2688, 
    "w": 118.1
  }, 
  {
    "a": 23.434, 
    "om": 73.896, 
    "e": 0.99, 
    "i": 127.35, 
    "q": 0.2349, 
    "w": 122.07
  }, 
  {
    "a": 16.937, 
    "om": 73.906, 
    "e": 0.985, 
    "i": 127.48, 
    "q": 0.2559, 
    "w": 119.46
  }, 
  {
    "a": 30.908, 
    "om": 73.929, 
    "e": 0.991, 
    "i": 129.9, 
    "q": 0.2768, 
    "w": 116.4
  }, 
  {
    "a": 4.154, 
    "om": 74.662, 
    "e": 0.935, 
    "i": 128.99, 
    "q": 0.2687, 
    "w": 120.32
  }, 
  {
    "a": 15.133, 
    "om": 74.691, 
    "e": 0.982, 
    "i": 128.12, 
    "q": 0.2684, 
    "w": 117.92
  }, 
  {
    "a": 31.238, 
    "om": 74.708, 
    "e": 0.992, 
    "i": 130.26, 
    "q": 0.2521, 
    "w": 119.63
  }, 
  {
    "a": 34.972, 
    "om": 74.726, 
    "e": 0.993, 
    "i": 130.33, 
    "q": 0.2554, 
    "w": 119.14
  }, 
  {
    "a": 36.455, 
    "om": 74.731, 
    "e": 0.994, 
    "i": 127.02, 
    "q": 0.2215, 
    "w": 123.71
  }, 
  {
    "a": 19.902, 
    "om": 74.733, 
    "e": 0.989, 
    "i": 128.12, 
    "q": 0.2248, 
    "w": 123.54
  }, 
  {
    "a": 31.24, 
    "om": 74.74, 
    "e": 0.992, 
    "i": 128.99, 
    "q": 0.2435, 
    "w": 120.77
  }, 
  {
    "a": 4.931, 
    "om": 74.747, 
    "e": 0.946, 
    "i": 128.09, 
    "q": 0.2665, 
    "w": 120.04
  }, 
  {
    "a": 13.526, 
    "om": 74.749, 
    "e": 0.981, 
    "i": 128.85, 
    "q": 0.2602, 
    "w": 119.1
  }, 
  {
    "a": 24.773, 
    "om": 74.776, 
    "e": 0.989, 
    "i": 128.3, 
    "q": 0.2609, 
    "w": 118.57
  }, 
  {
    "a": 8.406, 
    "om": 74.788, 
    "e": 0.964, 
    "i": 130.19, 
    "q": 0.3048, 
    "w": 114.03
  }, 
  {
    "a": 7.239, 
    "om": 74.806, 
    "e": 0.967, 
    "i": 128.42, 
    "q": 0.242, 
    "w": 122.34
  }, 
  {
    "a": 14.162, 
    "om": 74.809, 
    "e": 0.98, 
    "i": 128.45, 
    "q": 0.282, 
    "w": 116.23
  }, 
  {
    "a": 10.236, 
    "om": 74.82, 
    "e": 0.977, 
    "i": 127.82, 
    "q": 0.2341, 
    "w": 122.86
  }, 
  {
    "a": 13.905, 
    "om": 74.83, 
    "e": 0.983, 
    "i": 128.25, 
    "q": 0.2434, 
    "w": 121.29
  }, 
  {
    "a": 8.769, 
    "om": 74.833, 
    "e": 0.968, 
    "i": 125.07, 
    "q": 0.2808, 
    "w": 116.97
  }, 
  {
    "a": 8.943, 
    "om": 74.839, 
    "e": 0.972, 
    "i": 128.04, 
    "q": 0.2503, 
    "w": 120.89
  }, 
  {
    "a": 7.465, 
    "om": 74.864, 
    "e": 0.968, 
    "i": 128.57, 
    "q": 0.2411, 
    "w": 122.39
  }, 
  {
    "a": 19.912, 
    "om": 74.876, 
    "e": 0.987, 
    "i": 126.96, 
    "q": 0.2559, 
    "w": 119.35
  }, 
  {
    "a": 13.671, 
    "om": 74.878, 
    "e": 0.983, 
    "i": 128.3, 
    "q": 0.2347, 
    "w": 122.47
  }, 
  {
    "a": 6.52, 
    "om": 74.884, 
    "e": 0.964, 
    "i": 129.37, 
    "q": 0.234, 
    "w": 123.6
  }, 
  {
    "a": 16.174, 
    "om": 74.887, 
    "e": 0.986, 
    "i": 127.99, 
    "q": 0.228, 
    "w": 123.23
  }, 
  {
    "a": 15.463, 
    "om": 74.903, 
    "e": 0.979, 
    "i": 133.48, 
    "q": 0.3329, 
    "w": 109.8
  }, 
  {
    "a": 17.354, 
    "om": 74.911, 
    "e": 0.987, 
    "i": 131.47, 
    "q": 0.2269, 
    "w": 123.34
  }, 
  {
    "a": 3.964, 
    "om": 74.913, 
    "e": 0.939, 
    "i": 126.23, 
    "q": 0.24, 
    "w": 124.16
  }, 
  {
    "a": 7.031, 
    "om": 74.917, 
    "e": 0.966, 
    "i": 131.63, 
    "q": 0.2395, 
    "w": 122.72
  }, 
  {
    "a": 11.536, 
    "om": 74.92, 
    "e": 0.978, 
    "i": 128.53, 
    "q": 0.2567, 
    "w": 119.72
  }, 
  {
    "a": 24.39, 
    "om": 74.922, 
    "e": 0.99, 
    "i": 128.92, 
    "q": 0.2534, 
    "w": 119.57
  }, 
  {
    "a": 13.612, 
    "om": 74.948, 
    "e": 0.981, 
    "i": 128.27, 
    "q": 0.2616, 
    "w": 118.9
  }, 
  {
    "a": 11.27, 
    "om": 74.951, 
    "e": 0.975, 
    "i": 129.29, 
    "q": 0.2824, 
    "w": 116.43
  }, 
  {
    "a": 7.165, 
    "om": 75.67, 
    "e": 0.962, 
    "i": 129.31, 
    "q": 0.2687, 
    "w": 118.86
  }, 
  {
    "a": 10.155, 
    "om": 75.681, 
    "e": 0.975, 
    "i": 128.79, 
    "q": 0.2552, 
    "w": 120.06
  }, 
  {
    "a": 7.797, 
    "om": 75.71, 
    "e": 0.966, 
    "i": 126.71, 
    "q": 0.2655, 
    "w": 119.12
  }, 
  {
    "a": 23.386, 
    "om": 75.711, 
    "e": 0.99, 
    "i": 129.99, 
    "q": 0.2398, 
    "w": 121.4
  }, 
  {
    "a": 7.767, 
    "om": 75.715, 
    "e": 0.97, 
    "i": 128.32, 
    "q": 0.2318, 
    "w": 123.57
  }, 
  {
    "a": 43.335, 
    "om": 75.72, 
    "e": 0.993, 
    "i": 129.8, 
    "q": 0.2969, 
    "w": 113.7
  }, 
  {
    "a": 33.271, 
    "om": 75.727, 
    "e": 0.992, 
    "i": 127.29, 
    "q": 0.26, 
    "w": 118.55
  }, 
  {
    "a": 13.285, 
    "om": 75.741, 
    "e": 0.982, 
    "i": 127.57, 
    "q": 0.2407, 
    "w": 121.68
  }, 
  {
    "a": 37.538, 
    "om": 75.774, 
    "e": 0.993, 
    "i": 128.41, 
    "q": 0.2488, 
    "w": 119.99
  }, 
  {
    "a": 9.238, 
    "om": 75.778, 
    "e": 0.975, 
    "i": 127.12, 
    "q": 0.2302, 
    "w": 123.52
  }, 
  {
    "a": 18.224, 
    "om": 75.784, 
    "e": 0.986, 
    "i": 130.48, 
    "q": 0.2502, 
    "w": 120.16
  }, 
  {
    "a": 15.798, 
    "om": 75.792, 
    "e": 0.986, 
    "i": 126.97, 
    "q": 0.2167, 
    "w": 124.82
  }, 
  {
    "a": 6.582, 
    "om": 75.801, 
    "e": 0.964, 
    "i": 126.39, 
    "q": 0.2401, 
    "w": 122.76
  }, 
  {
    "a": 6.251, 
    "om": 75.804, 
    "e": 0.926, 
    "i": 140.54, 
    "q": 0.4652, 
    "w": 95.61
  }, 
  {
    "a": 5.497, 
    "om": 75.807, 
    "e": 0.949, 
    "i": 127.53, 
    "q": 0.2827, 
    "w": 117.69
  }, 
  {
    "a": 8.333, 
    "om": 75.807, 
    "e": 0.972, 
    "i": 126.56, 
    "q": 0.2349, 
    "w": 123.04
  }, 
  {
    "a": 9.764, 
    "om": 75.812, 
    "e": 0.974, 
    "i": 127.64, 
    "q": 0.2572, 
    "w": 119.86
  }, 
  {
    "a": 15.656, 
    "om": 75.844, 
    "e": 0.984, 
    "i": 128.89, 
    "q": 0.2498, 
    "w": 120.33
  }, 
  {
    "a": 2.736, 
    "om": 75.846, 
    "e": 0.873, 
    "i": 127.37, 
    "q": 0.3482, 
    "w": 112.79
  }, 
  {
    "a": 4.384, 
    "om": 75.85, 
    "e": 0.947, 
    "i": 126.32, 
    "q": 0.2317, 
    "w": 124.91
  }, 
  {
    "a": 8.853, 
    "om": 75.88, 
    "e": 0.973, 
    "i": 127.7, 
    "q": 0.2414, 
    "w": 122.07
  }, 
  {
    "a": 48.899, 
    "om": 75.927, 
    "e": 0.994, 
    "i": 130.38, 
    "q": 0.3013, 
    "w": 113.12
  }, 
  {
    "a": 73.214, 
    "om": 75.938, 
    "e": 0.997, 
    "i": 127.38, 
    "q": 0.2554, 
    "w": 118.95
  }, 
  {
    "a": 13.734, 
    "om": 75.941, 
    "e": 0.98, 
    "i": 128.58, 
    "q": 0.2767, 
    "w": 116.94
  }, 
  {
    "a": 12.881, 
    "om": 75.953, 
    "e": 0.983, 
    "i": 127.44, 
    "q": 0.223, 
    "w": 124.11
  }, 
  {
    "a": 23.133, 
    "om": 76.688, 
    "e": 0.99, 
    "i": 126.43, 
    "q": 0.2313, 
    "w": 122.55
  }, 
  {
    "a": 4.882, 
    "om": 76.694, 
    "e": 0.95, 
    "i": 128.28, 
    "q": 0.2447, 
    "w": 122.87
  }, 
  {
    "a": 8.319, 
    "om": 76.7, 
    "e": 0.966, 
    "i": 129.74, 
    "q": 0.2832, 
    "w": 116.75
  }, 
  {
    "a": 11.164, 
    "om": 76.774, 
    "e": 0.974, 
    "i": 128.05, 
    "q": 0.2898, 
    "w": 115.49
  }, 
  {
    "a": 16.899, 
    "om": 76.782, 
    "e": 0.986, 
    "i": 125.2, 
    "q": 0.2411, 
    "w": 121.43
  }, 
  {
    "a": 9.456, 
    "om": 76.795, 
    "e": 0.975, 
    "i": 125.86, 
    "q": 0.2349, 
    "w": 122.85
  }, 
  {
    "a": 50.242, 
    "om": 76.797, 
    "e": 0.994, 
    "i": 132.25, 
    "q": 0.2781, 
    "w": 116.06
  }, 
  {
    "a": 14.8, 
    "om": 76.807, 
    "e": 0.983, 
    "i": 128.9, 
    "q": 0.255, 
    "w": 119.68
  }, 
  {
    "a": 17.533, 
    "om": 76.826, 
    "e": 0.986, 
    "i": 128.15, 
    "q": 0.2489, 
    "w": 120.35
  }, 
  {
    "a": 14.123, 
    "om": 76.84, 
    "e": 0.982, 
    "i": 128.66, 
    "q": 0.2511, 
    "w": 120.24
  }, 
  {
    "a": 97.403, 
    "om": 76.847, 
    "e": 0.998, 
    "i": 126.63, 
    "q": 0.2438, 
    "w": 120.45
  }, 
  {
    "a": 14.04, 
    "om": 76.863, 
    "e": 0.981, 
    "i": 128.49, 
    "q": 0.2667, 
    "w": 118.2
  }, 
  {
    "a": 4.873, 
    "om": 76.864, 
    "e": 0.946, 
    "i": 129.77, 
    "q": 0.2644, 
    "w": 120.34
  }, 
  {
    "a": 22.095, 
    "om": 76.877, 
    "e": 0.987, 
    "i": 134.83, 
    "q": 0.2869, 
    "w": 115.27
  }, 
  {
    "a": 15.533, 
    "om": 76.878, 
    "e": 0.981, 
    "i": 129.32, 
    "q": 0.294, 
    "w": 114.62
  }, 
  {
    "a": 6.472, 
    "om": 76.881, 
    "e": 0.966, 
    "i": 125.04, 
    "q": 0.2223, 
    "w": 125.18
  }, 
  {
    "a": 5.967, 
    "om": 76.902, 
    "e": 0.958, 
    "i": 131.82, 
    "q": 0.2491, 
    "w": 121.78
  }, 
  {
    "a": 11.169, 
    "om": 76.915, 
    "e": 0.978, 
    "i": 128.51, 
    "q": 0.2505, 
    "w": 120.56
  }, 
  {
    "a": 11.58, 
    "om": 76.922, 
    "e": 0.978, 
    "i": 128.61, 
    "q": 0.2586, 
    "w": 119.45
  }, 
  {
    "a": 9.007, 
    "om": 76.967, 
    "e": 0.971, 
    "i": 128.46, 
    "q": 0.2614, 
    "w": 119.41
  }, 
  {
    "a": 15.654, 
    "om": 76.979, 
    "e": 0.984, 
    "i": 129.54, 
    "q": 0.2568, 
    "w": 119.4
  }, 
  {
    "a": 9.102, 
    "om": 76.983, 
    "e": 0.975, 
    "i": 127.66, 
    "q": 0.2278, 
    "w": 123.86
  }, 
  {
    "a": 21.673, 
    "om": 77.651, 
    "e": 0.989, 
    "i": 128.09, 
    "q": 0.2399, 
    "w": 121.42
  }, 
  {
    "a": 28.687, 
    "om": 77.701, 
    "e": 0.991, 
    "i": 131.38, 
    "q": 0.259, 
    "w": 118.73
  }, 
  {
    "a": 8.582, 
    "om": 77.719, 
    "e": 0.973, 
    "i": 127.27, 
    "q": 0.236, 
    "w": 122.84
  }, 
  {
    "a": 4.481, 
    "om": 77.741, 
    "e": 0.948, 
    "i": 126.54, 
    "q": 0.2344, 
    "w": 124.47
  }, 
  {
    "a": 6.27, 
    "om": 77.744, 
    "e": 0.956, 
    "i": 126.71, 
    "q": 0.2764, 
    "w": 118.15
  }, 
  {
    "a": 6.519, 
    "om": 77.748, 
    "e": 0.962, 
    "i": 125.44, 
    "q": 0.2445, 
    "w": 122.2
  }, 
  {
    "a": 27.287, 
    "om": 77.774, 
    "e": 0.99, 
    "i": 130.2, 
    "q": 0.2749, 
    "w": 116.68
  }, 
  {
    "a": 32.16, 
    "om": 77.793, 
    "e": 0.993, 
    "i": 126.84, 
    "q": 0.2419, 
    "w": 120.96
  }, 
  {
    "a": 28.714, 
    "om": 77.906, 
    "e": 0.99, 
    "i": 123.63, 
    "q": 0.2732, 
    "w": 116.88
  }, 
  {
    "a": 13.031, 
    "om": 77.924, 
    "e": 0.979, 
    "i": 125.72, 
    "q": 0.2685, 
    "w": 118.04
  }, 
  {
    "a": 21.238, 
    "om": 77.934, 
    "e": 0.989, 
    "i": 126.87, 
    "q": 0.2419, 
    "w": 121.16
  }, 
  {
    "a": 14.129, 
    "om": 77.964, 
    "e": 0.983, 
    "i": 126.9, 
    "q": 0.2474, 
    "w": 120.73
  }, 
  {
    "a": 8.837, 
    "om": 77.969, 
    "e": 0.971, 
    "i": 127.33, 
    "q": 0.2571, 
    "w": 120.0
  }, 
  {
    "a": 18.982, 
    "om": 77.976, 
    "e": 0.988, 
    "i": 126.61, 
    "q": 0.2212, 
    "w": 124.05
  }, 
  {
    "a": 22.598, 
    "om": 78.682, 
    "e": 0.99, 
    "i": 131.88, 
    "q": 0.2319, 
    "w": 122.47
  }, 
  {
    "a": 26.132, 
    "om": 80.8, 
    "e": 0.992, 
    "i": 126.51, 
    "q": 0.2135, 
    "w": 124.93
  }, 
  {
    "a": 15.703, 
    "om": 80.825, 
    "e": 0.984, 
    "i": 128.84, 
    "q": 0.2559, 
    "w": 119.5
  }, 
  {
    "a": 24.33, 
    "om": 80.841, 
    "e": 0.99, 
    "i": 126.25, 
    "q": 0.2339, 
    "w": 122.15
  }, 
  {
    "a": 9.933, 
    "om": 80.874, 
    "e": 0.966, 
    "i": 126.21, 
    "q": 0.3334, 
    "w": 110.23
  }, 
  {
    "a": 6.434, 
    "om": 80.88, 
    "e": 0.963, 
    "i": 124.7, 
    "q": 0.2402, 
    "w": 122.78
  }, 
  {
    "a": 4.219, 
    "om": 80.881, 
    "e": 0.945, 
    "i": 130.68, 
    "q": 0.232, 
    "w": 124.97
  }, 
  {
    "a": 6.095, 
    "om": 80.891, 
    "e": 0.955, 
    "i": 132.68, 
    "q": 0.2762, 
    "w": 118.23
  }, 
  {
    "a": 19.37, 
    "om": 80.926, 
    "e": 0.989, 
    "i": 131.57, 
    "q": 0.2155, 
    "w": 124.82
  }, 
  {
    "a": 11.84, 
    "om": 80.969, 
    "e": 0.978, 
    "i": 127.46, 
    "q": 0.2572, 
    "w": 119.6
  }, 
  {
    "a": 5.958, 
    "om": 81.011, 
    "e": 0.96, 
    "i": 127.62, 
    "q": 0.2396, 
    "w": 123.02
  }, 
  {
    "a": 90.776, 
    "om": 81.05, 
    "e": 0.997, 
    "i": 126.18, 
    "q": 0.2409, 
    "w": 120.84
  }, 
  {
    "a": 36.137, 
    "om": 81.735, 
    "e": 0.992, 
    "i": 128.3, 
    "q": 0.2832, 
    "w": 115.49
  }, 
  {
    "a": 11.782, 
    "om": 81.831, 
    "e": 0.981, 
    "i": 127.22, 
    "q": 0.2224, 
    "w": 124.27
  }, 
  {
    "a": 26.236, 
    "om": 81.858, 
    "e": 0.991, 
    "i": 126.41, 
    "q": 0.2289, 
    "w": 122.79
  }, 
  {
    "a": 28.48, 
    "om": 81.862, 
    "e": 0.991, 
    "i": 127.23, 
    "q": 0.2528, 
    "w": 119.54
  }, 
  {
    "a": 6.526, 
    "om": 81.92, 
    "e": 0.962, 
    "i": 124.96, 
    "q": 0.2505, 
    "w": 121.38
  }, 
  {
    "a": 13.626, 
    "om": 81.923, 
    "e": 0.98, 
    "i": 129.51, 
    "q": 0.2732, 
    "w": 117.36
  }, 
  {
    "a": 11.03, 
    "om": 81.947, 
    "e": 0.979, 
    "i": 126.19, 
    "q": 0.2267, 
    "w": 123.75
  }, 
  {
    "a": 7.195, 
    "om": 81.951, 
    "e": 0.958, 
    "i": 134.49, 
    "q": 0.3049, 
    "w": 114.27
  }, 
  {
    "a": 11.943, 
    "om": 81.968, 
    "e": 0.98, 
    "i": 129.87, 
    "q": 0.2356, 
    "w": 122.45
  }, 
  {
    "a": 11.034, 
    "om": 82.816, 
    "e": 0.978, 
    "i": 126.77, 
    "q": 0.2383, 
    "w": 122.18
  }, 
  {
    "a": 14.717, 
    "om": 83.812, 
    "e": 0.986, 
    "i": 125.3, 
    "q": 0.2076, 
    "w": 126.11
  }, 
  {
    "a": 6.243, 
    "om": 83.862, 
    "e": 0.959, 
    "i": 125.74, 
    "q": 0.2549, 
    "w": 120.9
  }, 
  {
    "a": 19.366, 
    "om": 83.905, 
    "e": 0.988, 
    "i": 126.36, 
    "q": 0.2328, 
    "w": 122.43
  }, 
  {
    "a": 9.002, 
    "om": 84.007, 
    "e": 0.975, 
    "i": 124.88, 
    "q": 0.2275, 
    "w": 123.89
  }, 
  {
    "a": 5.993, 
    "om": 84.062, 
    "e": 0.961, 
    "i": 125.86, 
    "q": 0.2327, 
    "w": 123.91
  }, 
  {
    "a": 10.499, 
    "om": 84.069, 
    "e": 0.974, 
    "i": 130.82, 
    "q": 0.2698, 
    "w": 118.09
  }, 
  {
    "a": 19.637, 
    "om": 84.084, 
    "e": 0.989, 
    "i": 126.89, 
    "q": 0.2059, 
    "w": 126.16
  }, 
  {
    "a": 4.273, 
    "om": 84.091, 
    "e": 0.929, 
    "i": 129.1, 
    "q": 0.3037, 
    "w": 115.83
  }, 
  {
    "a": 9.994, 
    "om": 84.106, 
    "e": 0.975, 
    "i": 131.99, 
    "q": 0.2514, 
    "w": 120.55
  }, 
  {
    "a": 16.533, 
    "om": 84.891, 
    "e": 0.986, 
    "i": 128.15, 
    "q": 0.2367, 
    "w": 122.01
  }, 
  {
    "a": 6.709, 
    "om": 84.905, 
    "e": 0.965, 
    "i": 124.53, 
    "q": 0.2329, 
    "w": 123.65
  }, 
  {
    "a": 6.591, 
    "om": 84.913, 
    "e": 0.967, 
    "i": 130.05, 
    "q": 0.2199, 
    "w": 125.44
  }, 
  {
    "a": 10.205, 
    "om": 84.924, 
    "e": 0.975, 
    "i": 127.72, 
    "q": 0.2591, 
    "w": 119.51
  }, 
  {
    "a": 21.664, 
    "om": 84.925, 
    "e": 0.988, 
    "i": 132.16, 
    "q": 0.2627, 
    "w": 118.37
  }, 
  {
    "a": 8.415, 
    "om": 84.932, 
    "e": 0.969, 
    "i": 128.85, 
    "q": 0.2647, 
    "w": 119.06
  }, 
  {
    "a": 9.072, 
    "om": 84.962, 
    "e": 0.975, 
    "i": 123.05, 
    "q": 0.2237, 
    "w": 124.4
  }, 
  {
    "a": 17.884, 
    "om": 85.021, 
    "e": 0.986, 
    "i": 124.97, 
    "q": 0.2486, 
    "w": 120.35
  }, 
  {
    "a": 382.619, 
    "om": 85.034, 
    "e": 0.999, 
    "i": 125.9, 
    "q": 0.2001, 
    "w": 126.42
  }, 
  {
    "a": 11.395, 
    "om": 85.074, 
    "e": 0.977, 
    "i": 128.14, 
    "q": 0.2631, 
    "w": 118.86
  }, 
  {
    "a": 3.377, 
    "om": 85.843, 
    "e": 0.931, 
    "i": 130.69, 
    "q": 0.2315, 
    "w": 125.86
  }, 
  {
    "a": 17.902, 
    "om": 85.844, 
    "e": 0.987, 
    "i": 127.45, 
    "q": 0.2352, 
    "w": 122.14
  }, 
  {
    "a": 12.964, 
    "om": 85.879, 
    "e": 0.983, 
    "i": 125.96, 
    "q": 0.224, 
    "w": 123.94
  }, 
  {
    "a": 58.994, 
    "om": 85.908, 
    "e": 0.996, 
    "i": 125.98, 
    "q": 0.229, 
    "w": 122.52
  }, 
  {
    "a": 17.155, 
    "om": 85.954, 
    "e": 0.988, 
    "i": 127.75, 
    "q": 0.2067, 
    "w": 126.13
  }, 
  {
    "a": 19.421, 
    "om": 85.978, 
    "e": 0.987, 
    "i": 131.11, 
    "q": 0.2489, 
    "w": 120.25
  }, 
  {
    "a": 5.064, 
    "om": 85.987, 
    "e": 0.943, 
    "i": 129.9, 
    "q": 0.2887, 
    "w": 117.13
  }, 
  {
    "a": 77.843, 
    "om": 85.993, 
    "e": 0.995, 
    "i": 137.92, 
    "q": 0.3646, 
    "w": 105.19
  }, 
  {
    "a": 3.432, 
    "om": 86.022, 
    "e": 0.925, 
    "i": 131.65, 
    "q": 0.2586, 
    "w": 122.31
  }, 
  {
    "a": 9.442, 
    "om": 86.045, 
    "e": 0.979, 
    "i": 127.54, 
    "q": 0.1951, 
    "w": 128.34
  }, 
  {
    "a": 54.399, 
    "om": 86.057, 
    "e": 0.995, 
    "i": 123.28, 
    "q": 0.2634, 
    "w": 117.91
  }, 
  {
    "a": 7.335, 
    "om": 86.06, 
    "e": 0.973, 
    "i": 129.18, 
    "q": 0.2012, 
    "w": 127.84
  }, 
  {
    "a": 63.374, 
    "om": 86.102, 
    "e": 0.994, 
    "i": 130.92, 
    "q": 0.3462, 
    "w": 107.46
  }, 
  {
    "a": 153.206, 
    "om": 86.109, 
    "e": 0.998, 
    "i": 128.64, 
    "q": 0.2507, 
    "w": 119.45
  }, 
  {
    "a": 4.057, 
    "om": 86.117, 
    "e": 0.937, 
    "i": 124.06, 
    "q": 0.2563, 
    "w": 121.93
  }, 
  {
    "a": 39.96, 
    "om": 86.942, 
    "e": 0.994, 
    "i": 129.15, 
    "q": 0.24, 
    "w": 121.12
  }, 
  {
    "a": 2.062, 
    "om": 86.961, 
    "e": 0.876, 
    "i": 122.38, 
    "q": 0.2552, 
    "w": 125.86
  }, 
  {
    "a": 96.101, 
    "om": 87.794, 
    "e": 0.998, 
    "i": 124.33, 
    "q": 0.2107, 
    "w": 124.99
  }, 
  {
    "a": 3.207, 
    "om": 87.93, 
    "e": 0.925, 
    "i": 129.78, 
    "q": 0.2405, 
    "w": 124.91
  }, 
  {
    "a": 70.752, 
    "om": 87.996, 
    "e": 0.996, 
    "i": 131.05, 
    "q": 0.2749, 
    "w": 116.36
  }, 
  {
    "a": 124.5, 
    "om": 88.01, 
    "e": 0.998, 
    "i": 126.54, 
    "q": 0.2533, 
    "w": 119.12
  }, 
  {
    "a": 385.585, 
    "om": 88.101, 
    "e": 0.999, 
    "i": 129.92, 
    "q": 0.3145, 
    "w": 111.18
  }, 
  {
    "a": 7.282, 
    "om": 88.142, 
    "e": 0.965, 
    "i": 133.27, 
    "q": 0.2533, 
    "w": 120.79
  }, 
  {
    "a": 19.369, 
    "om": 88.161, 
    "e": 0.982, 
    "i": 132.41, 
    "q": 0.3579, 
    "w": 106.52
  }, 
  {
    "a": 21.312, 
    "om": 88.97, 
    "e": 0.989, 
    "i": 121.74, 
    "q": 0.2432, 
    "w": 120.94
  }, 
  {
    "a": 11.214, 
    "om": 89.066, 
    "e": 0.978, 
    "i": 127.43, 
    "q": 0.2476, 
    "w": 120.9
  }, 
  {
    "a": 9.41, 
    "om": 89.085, 
    "e": 0.975, 
    "i": 131.15, 
    "q": 0.2392, 
    "w": 122.24
  }, 
  {
    "a": 14.618, 
    "om": 89.086, 
    "e": 0.978, 
    "i": 131.5, 
    "q": 0.3214, 
    "w": 111.2
  }, 
  {
    "a": 8.554, 
    "om": 89.124, 
    "e": 0.975, 
    "i": 124.63, 
    "q": 0.2102, 
    "w": 126.33
  }, 
  {
    "a": 10.354, 
    "om": 90.051, 
    "e": 0.976, 
    "i": 123.45, 
    "q": 0.247, 
    "w": 121.07
  }, 
  {
    "a": 5.138, 
    "om": 90.074, 
    "e": 0.952, 
    "i": 120.04, 
    "q": 0.2466, 
    "w": 122.45
  }, 
  {
    "a": 10.124, 
    "om": 90.077, 
    "e": 0.976, 
    "i": 123.65, 
    "q": 0.2391, 
    "w": 122.16
  }, 
  {
    "a": 7.51, 
    "om": 90.19, 
    "e": 0.97, 
    "i": 123.49, 
    "q": 0.2212, 
    "w": 125.02
  }, 
  {
    "a": 5.224, 
    "om": 90.196, 
    "e": 0.96, 
    "i": 128.81, 
    "q": 0.211, 
    "w": 127.17
  }, 
  {
    "a": 4.611, 
    "om": 91.003, 
    "e": 0.952, 
    "i": 121.63, 
    "q": 0.2195, 
    "w": 126.34
  }, 
  {
    "a": 16.433, 
    "om": 91.019, 
    "e": 0.987, 
    "i": 122.0, 
    "q": 0.2141, 
    "w": 125.1
  }, 
  {
    "a": 5.326, 
    "om": 91.082, 
    "e": 0.962, 
    "i": 124.4, 
    "q": 0.2012, 
    "w": 128.48
  }, 
  {
    "a": 7.752, 
    "om": 91.969, 
    "e": 0.974, 
    "i": 121.25, 
    "q": 0.2041, 
    "w": 127.33
  }, 
  {
    "a": 10.397, 
    "om": 91.975, 
    "e": 0.976, 
    "i": 132.64, 
    "q": 0.2539, 
    "w": 120.16
  }, 
  {
    "a": 8.885, 
    "om": 92.141, 
    "e": 0.978, 
    "i": 121.79, 
    "q": 0.1995, 
    "w": 127.79
  }, 
  {
    "a": 13.594, 
    "om": 92.972, 
    "e": 0.983, 
    "i": 131.92, 
    "q": 0.2324, 
    "w": 122.73
  }, 
  {
    "a": 36.737, 
    "om": 93.093, 
    "e": 0.993, 
    "i": 127.23, 
    "q": 0.2488, 
    "w": 119.95
  }, 
  {
    "a": 38.235, 
    "om": 93.159, 
    "e": 0.993, 
    "i": 128.72, 
    "q": 0.2514, 
    "w": 119.58
  }, 
  {
    "a": 102.054, 
    "om": 94.296, 
    "e": 0.998, 
    "i": 122.49, 
    "q": 0.2181, 
    "w": 123.93
  }, 
  {
    "a": 6.427, 
    "om": 9.5, 
    "e": 0.847, 
    "i": 174.94, 
    "q": 0.9847, 
    "w": 344.83
  }, 
  {
    "a": 6.582, 
    "om": 14.425, 
    "e": 0.849, 
    "i": 176.79, 
    "q": 0.9969, 
    "w": 354.15
  }, 
  {
    "a": 31.676, 
    "om": 14.461, 
    "e": 0.969, 
    "i": 175.9, 
    "q": 0.9944, 
    "w": 351.93
  }, 
  {
    "a": 7.209, 
    "om": 62.368, 
    "e": 0.959, 
    "i": 133.22, 
    "q": 0.2989, 
    "w": 115.12
  }, 
  {
    "a": 53.688, 
    "om": 63.388, 
    "e": 0.994, 
    "i": 132.07, 
    "q": 0.3027, 
    "w": 112.98
  }, 
  {
    "a": 5.393, 
    "om": 63.439, 
    "e": 0.948, 
    "i": 132.06, 
    "q": 0.2794, 
    "w": 118.23
  }, 
  {
    "a": 19.591, 
    "om": 64.406, 
    "e": 0.986, 
    "i": 132.3, 
    "q": 0.2827, 
    "w": 115.94
  }, 
  {
    "a": 2.793, 
    "om": 75.464, 
    "e": 0.865, 
    "i": 137.93, 
    "q": 0.3766, 
    "w": 109.38
  }, 
  {
    "a": 7.66, 
    "om": 75.636, 
    "e": 0.968, 
    "i": 128.59, 
    "q": 0.2467, 
    "w": 121.61
  }, 
  {
    "a": 12.167, 
    "om": 75.672, 
    "e": 0.979, 
    "i": 130.25, 
    "q": 0.2512, 
    "w": 120.38
  }, 
  {
    "a": 6.349, 
    "om": 75.675, 
    "e": 0.965, 
    "i": 127.04, 
    "q": 0.2199, 
    "w": 125.55
  }, 
  {
    "a": 53.04, 
    "om": 76.431, 
    "e": 0.995, 
    "i": 127.71, 
    "q": 0.2524, 
    "w": 119.41
  }, 
  {
    "a": 5.018, 
    "om": 76.495, 
    "e": 0.948, 
    "i": 128.71, 
    "q": 0.2616, 
    "w": 120.61
  }, 
  {
    "a": 10.89, 
    "om": 76.528, 
    "e": 0.975, 
    "i": 133.02, 
    "q": 0.2701, 
    "w": 118.04
  }, 
  {
    "a": 16.571, 
    "om": 76.529, 
    "e": 0.984, 
    "i": 131.5, 
    "q": 0.267, 
    "w": 118.02
  }, 
  {
    "a": 15.035, 
    "om": 76.634, 
    "e": 0.984, 
    "i": 127.21, 
    "q": 0.2375, 
    "w": 122.01
  }, 
  {
    "a": 3.746, 
    "om": 76.691, 
    "e": 0.937, 
    "i": 126.58, 
    "q": 0.2351, 
    "w": 125.0
  }, 
  {
    "a": 12.171, 
    "om": 77.455, 
    "e": 0.981, 
    "i": 127.55, 
    "q": 0.2352, 
    "w": 122.5
  }, 
  {
    "a": 9.684, 
    "om": 77.468, 
    "e": 0.977, 
    "i": 126.79, 
    "q": 0.2219, 
    "w": 124.57
  }, 
  {
    "a": 7.619, 
    "om": 77.537, 
    "e": 0.974, 
    "i": 121.73, 
    "q": 0.1972, 
    "w": 128.37
  }, 
  {
    "a": 4.924, 
    "om": 77.54, 
    "e": 0.952, 
    "i": 130.16, 
    "q": 0.2362, 
    "w": 123.96
  }, 
  {
    "a": 12.835, 
    "om": 77.567, 
    "e": 0.981, 
    "i": 128.36, 
    "q": 0.2455, 
    "w": 121.08
  }, 
  {
    "a": 15.9, 
    "om": 77.575, 
    "e": 0.985, 
    "i": 128.55, 
    "q": 0.2421, 
    "w": 121.34
  }, 
  {
    "a": 27.815, 
    "om": 77.604, 
    "e": 0.992, 
    "i": 126.65, 
    "q": 0.2272, 
    "w": 123.01
  }, 
  {
    "a": 10.177, 
    "om": 77.607, 
    "e": 0.978, 
    "i": 126.51, 
    "q": 0.2224, 
    "w": 124.45
  }, 
  {
    "a": 8.967, 
    "om": 77.611, 
    "e": 0.973, 
    "i": 129.97, 
    "q": 0.2391, 
    "w": 122.36
  }, 
  {
    "a": 30.88, 
    "om": 77.63, 
    "e": 0.992, 
    "i": 127.84, 
    "q": 0.2341, 
    "w": 122.03
  }, 
  {
    "a": 7.247, 
    "om": 77.676, 
    "e": 0.962, 
    "i": 122.54, 
    "q": 0.2782, 
    "w": 117.62
  }, 
  {
    "a": 28.353, 
    "om": 78.398, 
    "e": 0.99, 
    "i": 128.88, 
    "q": 0.287, 
    "w": 115.11
  }, 
  {
    "a": 113.818, 
    "om": 78.478, 
    "e": 0.998, 
    "i": 130.25, 
    "q": 0.2351, 
    "w": 121.6
  }, 
  {
    "a": 13.421, 
    "om": 78.506, 
    "e": 0.985, 
    "i": 124.21, 
    "q": 0.2013, 
    "w": 127.11
  }, 
  {
    "a": 12.89, 
    "om": 78.536, 
    "e": 0.984, 
    "i": 124.91, 
    "q": 0.2006, 
    "w": 127.24
  }, 
  {
    "a": 11.211, 
    "om": 78.541, 
    "e": 0.978, 
    "i": 124.29, 
    "q": 0.2503, 
    "w": 120.58
  }, 
  {
    "a": 9.494, 
    "om": 78.562, 
    "e": 0.975, 
    "i": 126.65, 
    "q": 0.2404, 
    "w": 122.1
  }, 
  {
    "a": 13.772, 
    "om": 78.568, 
    "e": 0.982, 
    "i": 128.97, 
    "q": 0.2448, 
    "w": 121.09
  }, 
  {
    "a": 6.047, 
    "om": 78.58, 
    "e": 0.964, 
    "i": 125.56, 
    "q": 0.2169, 
    "w": 126.05
  }, 
  {
    "a": 17.126, 
    "om": 78.583, 
    "e": 0.986, 
    "i": 128.82, 
    "q": 0.2421, 
    "w": 121.27
  }, 
  {
    "a": 7.994, 
    "om": 78.586, 
    "e": 0.974, 
    "i": 124.97, 
    "q": 0.2105, 
    "w": 126.43
  }, 
  {
    "a": 2.31, 
    "om": 78.597, 
    "e": 0.899, 
    "i": 124.6, 
    "q": 0.2344, 
    "w": 127.59
  }, 
  {
    "a": 53.797, 
    "om": 78.629, 
    "e": 0.995, 
    "i": 129.4, 
    "q": 0.2598, 
    "w": 118.42
  }, 
  {
    "a": 133.442, 
    "om": 78.656, 
    "e": 0.998, 
    "i": 128.27, 
    "q": 0.254, 
    "w": 119.05
  }, 
  {
    "a": 5.364, 
    "om": 79.443, 
    "e": 0.951, 
    "i": 129.87, 
    "q": 0.264, 
    "w": 120.11
  }, 
  {
    "a": 9.597, 
    "om": 79.459, 
    "e": 0.975, 
    "i": 127.27, 
    "q": 0.2422, 
    "w": 121.83
  }, 
  {
    "a": 7.105, 
    "om": 79.491, 
    "e": 0.957, 
    "i": 127.72, 
    "q": 0.307, 
    "w": 114.05
  }, 
  {
    "a": 10.976, 
    "om": 79.591, 
    "e": 0.978, 
    "i": 128.07, 
    "q": 0.2422, 
    "w": 121.67
  }, 
  {
    "a": 7.016, 
    "om": 79.602, 
    "e": 0.964, 
    "i": 125.31, 
    "q": 0.2527, 
    "w": 120.97
  }, 
  {
    "a": 13.913, 
    "om": 79.643, 
    "e": 0.983, 
    "i": 126.34, 
    "q": 0.2406, 
    "w": 121.64
  }, 
  {
    "a": 12.063, 
    "om": 79.65, 
    "e": 0.979, 
    "i": 126.99, 
    "q": 0.251, 
    "w": 120.4
  }, 
  {
    "a": 5.917, 
    "om": 79.665, 
    "e": 0.96, 
    "i": 125.11, 
    "q": 0.2383, 
    "w": 123.21
  }, 
  {
    "a": 13.991, 
    "om": 79.673, 
    "e": 0.979, 
    "i": 133.89, 
    "q": 0.289, 
    "w": 115.34
  }, 
  {
    "a": 6.71, 
    "om": 79.726, 
    "e": 0.964, 
    "i": 124.88, 
    "q": 0.2393, 
    "w": 122.81
  }, 
  {
    "a": 8.777, 
    "om": 79.751, 
    "e": 0.971, 
    "i": 124.4, 
    "q": 0.2544, 
    "w": 120.36
  }, 
  {
    "a": 14.428, 
    "om": 79.782, 
    "e": 0.983, 
    "i": 128.91, 
    "q": 0.2449, 
    "w": 121.03
  }, 
  {
    "a": 4.442, 
    "om": 81.443, 
    "e": 0.946, 
    "i": 131.29, 
    "q": 0.2394, 
    "w": 123.84
  }, 
  {
    "a": 662.882, 
    "om": 81.548, 
    "e": 1.0, 
    "i": 129.3, 
    "q": 0.2505, 
    "w": 119.43
  }, 
  {
    "a": 11.737, 
    "om": 81.57, 
    "e": 0.978, 
    "i": 123.07, 
    "q": 0.2605, 
    "w": 119.18
  }, 
  {
    "a": 9.045, 
    "om": 81.594, 
    "e": 0.973, 
    "i": 125.82, 
    "q": 0.2457, 
    "w": 121.45
  }, 
  {
    "a": 72.372, 
    "om": 81.599, 
    "e": 0.996, 
    "i": 127.87, 
    "q": 0.2601, 
    "w": 118.31
  }, 
  {
    "a": 16.162, 
    "om": 81.632, 
    "e": 0.983, 
    "i": 129.88, 
    "q": 0.2764, 
    "w": 116.8
  }, 
  {
    "a": 49.273, 
    "om": 81.669, 
    "e": 0.995, 
    "i": 125.77, 
    "q": 0.2264, 
    "w": 122.93
  }, 
  {
    "a": 12.22, 
    "om": 81.675, 
    "e": 0.979, 
    "i": 127.72, 
    "q": 0.2598, 
    "w": 119.22
  }, 
  {
    "a": 4.203, 
    "om": 81.688, 
    "e": 0.941, 
    "i": 128.17, 
    "q": 0.2465, 
    "w": 123.09
  }, 
  {
    "a": 6.1, 
    "om": 81.689, 
    "e": 0.959, 
    "i": 125.66, 
    "q": 0.2496, 
    "w": 121.65
  }, 
  {
    "a": 11.915, 
    "om": 81.69, 
    "e": 0.982, 
    "i": 124.83, 
    "q": 0.2186, 
    "w": 124.78
  }, 
  {
    "a": 28.632, 
    "om": 81.695, 
    "e": 0.991, 
    "i": 128.28, 
    "q": 0.261, 
    "w": 118.45
  }, 
  {
    "a": 10.254, 
    "om": 81.789, 
    "e": 0.976, 
    "i": 129.72, 
    "q": 0.2408, 
    "w": 121.93
  }, 
  {
    "a": 737.257, 
    "om": 81.792, 
    "e": 1.0, 
    "i": 127.05, 
    "q": 0.2566, 
    "w": 118.62
  }, 
  {
    "a": 1.923, 
    "om": 81.792, 
    "e": 0.872, 
    "i": 126.19, 
    "q": 0.2472, 
    "w": 127.47
  }, 
  {
    "a": 7.311, 
    "om": 81.801, 
    "e": 0.966, 
    "i": 127.16, 
    "q": 0.2473, 
    "w": 121.59
  }, 
  {
    "a": 5.926, 
    "om": 82.502, 
    "e": 0.96, 
    "i": 119.91, 
    "q": 0.2366, 
    "w": 123.43
  }, 
  {
    "a": 3.446, 
    "om": 82.546, 
    "e": 0.924, 
    "i": 128.24, 
    "q": 0.2603, 
    "w": 122.09
  }, 
  {
    "a": 7.055, 
    "om": 82.559, 
    "e": 0.97, 
    "i": 122.57, 
    "q": 0.2088, 
    "w": 126.85
  }, 
  {
    "a": 3.938, 
    "om": 82.652, 
    "e": 0.93, 
    "i": 134.99, 
    "q": 0.2765, 
    "w": 119.5
  }, 
  {
    "a": 4.115, 
    "om": 82.691, 
    "e": 0.943, 
    "i": 122.87, 
    "q": 0.2349, 
    "w": 124.66
  }, 
  {
    "a": 7.273, 
    "om": 82.777, 
    "e": 0.967, 
    "i": 125.1, 
    "q": 0.2401, 
    "w": 122.55
  }, 
  {
    "a": 19.217, 
    "om": 83.652, 
    "e": 0.989, 
    "i": 126.47, 
    "q": 0.2181, 
    "w": 124.45
  }, 
  {
    "a": 3.636, 
    "om": 83.708, 
    "e": 0.933, 
    "i": 123.74, 
    "q": 0.2427, 
    "w": 124.1
  }, 
  {
    "a": 17.833, 
    "om": 83.722, 
    "e": 0.989, 
    "i": 125.43, 
    "q": 0.1942, 
    "w": 127.89
  }, 
  {
    "a": 5.776, 
    "om": 83.737, 
    "e": 0.959, 
    "i": 127.28, 
    "q": 0.2359, 
    "w": 123.57
  }, 
  {
    "a": 9.29, 
    "om": 83.737, 
    "e": 0.975, 
    "i": 129.87, 
    "q": 0.2334, 
    "w": 123.04
  }, 
  {
    "a": 19.143, 
    "om": 83.74, 
    "e": 0.988, 
    "i": 126.61, 
    "q": 0.2382, 
    "w": 121.71
  }, 
  {
    "a": 10.772, 
    "om": 83.766, 
    "e": 0.985, 
    "i": 127.68, 
    "q": 0.1637, 
    "w": 132.87
  }, 
  {
    "a": 11.178, 
    "om": 83.811, 
    "e": 0.968, 
    "i": 141.03, 
    "q": 0.3574, 
    "w": 107.14
  }, 
  {
    "a": 72.103, 
    "om": 84.831, 
    "e": 0.997, 
    "i": 128.76, 
    "q": 0.2504, 
    "w": 119.58
  }, 
  {
    "a": 5.542, 
    "om": 84.844, 
    "e": 0.956, 
    "i": 120.39, 
    "q": 0.2413, 
    "w": 122.96
  }, 
  {
    "a": 10.628, 
    "om": 86.875, 
    "e": 0.977, 
    "i": 128.11, 
    "q": 0.2433, 
    "w": 121.53
  }, 
  {
    "a": 38.875, 
    "om": 87.56, 
    "e": 0.994, 
    "i": 125.72, 
    "q": 0.2482, 
    "w": 120.01
  }, 
  {
    "a": 9.646, 
    "om": 87.664, 
    "e": 0.977, 
    "i": 132.15, 
    "q": 0.2194, 
    "w": 124.9
  }, 
  {
    "a": 4.192, 
    "om": 87.697, 
    "e": 0.924, 
    "i": 138.4, 
    "q": 0.3196, 
    "w": 113.96
  }, 
  {
    "a": 44.809, 
    "om": 88.675, 
    "e": 0.995, 
    "i": 130.99, 
    "q": 0.2215, 
    "w": 123.61
  }, 
  {
    "a": 8.623, 
    "om": 88.802, 
    "e": 0.979, 
    "i": 131.16, 
    "q": 0.184, 
    "w": 130.07
  }, 
  {
    "a": 2.916, 
    "om": 88.861, 
    "e": 0.923, 
    "i": 127.17, 
    "q": 0.2243, 
    "w": 127.47
  }, 
  {
    "a": 15.826, 
    "om": 88.937, 
    "e": 0.988, 
    "i": 123.32, 
    "q": 0.1917, 
    "w": 128.32
  }
]