[
  {
    "a": 1.92, 
    "om": 350.232, 
    "e": 0.893, 
    "i": 4.8, 
    "q": 0.2048, 
    "w": 133.49
  }, 
  {
    "a": 2.301, 
    "om": 351.012, 
    "e": 0.91, 
    "i": 6.9, 
    "q": 0.206, 
    "w": 131.98
  }, 
  {
    "a": 1.399, 
    "om": 352.156, 
    "e": 0.819, 
    "i": 7.84, 
    "q": 0.2526, 
    "w": 131.51
  }, 
  {
    "a": 1.718, 
    "om": 352.968, 
    "e": 0.874, 
    "i": 4.77, 
    "q": 0.2165, 
    "w": 133.05
  }, 
  {
    "a": 1.305, 
    "om": 353.029, 
    "e": 0.844, 
    "i": 5.31, 
    "q": 0.2032, 
    "w": 137.99
  }, 
  {
    "a": 2.195, 
    "om": 353.118, 
    "e": 0.9, 
    "i": 4.02, 
    "q": 0.2191, 
    "w": 130.62
  }, 
  {
    "a": 1.826, 
    "om": 354.006, 
    "e": 0.875, 
    "i": 4.25, 
    "q": 0.2283, 
    "w": 131.03
  }, 
  {
    "a": 1.996, 
    "om": 354.028, 
    "e": 0.877, 
    "i": 3.56, 
    "q": 0.2463, 
    "w": 128.06
  }, 
  {
    "a": 2.708, 
    "om": 354.046, 
    "e": 0.928, 
    "i": 9.58, 
    "q": 0.1938, 
    "w": 132.59
  }, 
  {
    "a": 1.433, 
    "om": 355.91, 
    "e": 0.806, 
    "i": 7.27, 
    "q": 0.2785, 
    "w": 128.32
  }, 
  {
    "a": 1.886, 
    "om": 356.072, 
    "e": 0.867, 
    "i": 8.29, 
    "q": 0.2507, 
    "w": 128.02
  }, 
  {
    "a": 1.343, 
    "om": 356.07, 
    "e": 0.788, 
    "i": 3.49, 
    "q": 0.2846, 
    "w": 128.77
  }, 
  {
    "a": 2.47, 
    "om": 356.83, 
    "e": 0.899, 
    "i": 4.95, 
    "q": 0.2491, 
    "w": 126.06
  }, 
  {
    "a": 1.667, 
    "om": 356.957, 
    "e": 0.858, 
    "i": 4.39, 
    "q": 0.2371, 
    "w": 130.89
  }, 
  {
    "a": 1.46, 
    "om": 357.846, 
    "e": 0.832, 
    "i": 3.49, 
    "q": 0.2447, 
    "w": 131.69
  }, 
  {
    "a": 2.075, 
    "om": 357.994, 
    "e": 0.878, 
    "i": 5.29, 
    "q": 0.2526, 
    "w": 126.92
  }, 
  {
    "a": 1.398, 
    "om": 357.997, 
    "e": 0.812, 
    "i": 5.8, 
    "q": 0.2625, 
    "w": 130.39
  }, 
  {
    "a": 1.96, 
    "om": 358.725, 
    "e": 0.861, 
    "i": 5.62, 
    "q": 0.2724, 
    "w": 125.11
  }, 
  {
    "a": 1.433, 
    "om": 358.737, 
    "e": 0.816, 
    "i": 5.85, 
    "q": 0.2633, 
    "w": 129.91
  }, 
  {
    "a": 1.17, 
    "om": 359.907, 
    "e": 0.777, 
    "i": 5.71, 
    "q": 0.261, 
    "w": 133.82
  }, 
  {
    "a": 1.113, 
    "om": 2.776, 
    "e": 0.769, 
    "i": 7.92, 
    "q": 0.2576, 
    "w": 135.25
  }, 
  {
    "a": 1.192, 
    "om": 3.851, 
    "e": 0.788, 
    "i": 4.53, 
    "q": 0.2532, 
    "w": 134.15
  }, 
  {
    "a": 1.01, 
    "om": 4.728, 
    "e": 0.773, 
    "i": 5.81, 
    "q": 0.2291, 
    "w": 140.29
  }, 
  {
    "a": 1.685, 
    "om": 345.073, 
    "e": 0.889, 
    "i": 4.5, 
    "q": 0.1866, 
    "w": 136.99
  }, 
  {
    "a": 1.23, 
    "om": 351.76, 
    "e": 0.79, 
    "i": 5.47, 
    "q": 0.2576, 
    "w": 133.25
  }, 
  {
    "a": 1.551, 
    "om": 351.765, 
    "e": 0.832, 
    "i": 4.93, 
    "q": 0.2603, 
    "w": 129.21
  }, 
  {
    "a": 1.953, 
    "om": 352.822, 
    "e": 0.896, 
    "i": 7.07, 
    "q": 0.2029, 
    "w": 133.55
  }, 
  {
    "a": 1.724, 
    "om": 353.584, 
    "e": 0.877, 
    "i": 4.59, 
    "q": 0.2118, 
    "w": 133.59
  }, 
  {
    "a": 1.961, 
    "om": 353.634, 
    "e": 0.886, 
    "i": 5.89, 
    "q": 0.2239, 
    "w": 130.92
  }, 
  {
    "a": 1.592, 
    "om": 353.694, 
    "e": 0.878, 
    "i": 3.73, 
    "q": 0.1942, 
    "w": 136.56
  }, 
  {
    "a": 2.528, 
    "om": 354.739, 
    "e": 0.924, 
    "i": 3.55, 
    "q": 0.1923, 
    "w": 133.16
  }, 
  {
    "a": 1.191, 
    "om": 355.616, 
    "e": 0.757, 
    "i": 6.14, 
    "q": 0.2892, 
    "w": 130.76
  }, 
  {
    "a": 1.649, 
    "om": 355.726, 
    "e": 0.837, 
    "i": 4.73, 
    "q": 0.2692, 
    "w": 127.39
  }, 
  {
    "a": 1.695, 
    "om": 356.552, 
    "e": 0.835, 
    "i": 5.97, 
    "q": 0.2803, 
    "w": 125.81
  }, 
  {
    "a": 1.205, 
    "om": 356.714, 
    "e": 0.789, 
    "i": 6.71, 
    "q": 0.2541, 
    "w": 133.93
  }, 
  {
    "a": 1.668, 
    "om": 358.517, 
    "e": 0.858, 
    "i": 5.64, 
    "q": 0.2373, 
    "w": 130.85
  }, 
  {
    "a": 1.539, 
    "om": 358.574, 
    "e": 0.843, 
    "i": 5.59, 
    "q": 0.2411, 
    "w": 131.38
  }, 
  {
    "a": 1.694, 
    "om": 358.723, 
    "e": 0.839, 
    "i": 4.99, 
    "q": 0.273, 
    "w": 126.59
  }, 
  {
    "a": 1.168, 
    "om": 358.716, 
    "e": 0.77, 
    "i": 2.25, 
    "q": 0.2684, 
    "w": 133.17
  }, 
  {
    "a": 1.069, 
    "om": 358.765, 
    "e": 0.776, 
    "i": 5.95, 
    "q": 0.2396, 
    "w": 137.96
  }, 
  {
    "a": 1.482, 
    "om": 359.516, 
    "e": 0.82, 
    "i": 6.19, 
    "q": 0.2673, 
    "w": 128.98
  }, 
  {
    "a": 1.057, 
    "om": 0.66, 
    "e": 0.76, 
    "i": 3.83, 
    "q": 0.2542, 
    "w": 136.86
  }, 
  {
    "a": 1.025, 
    "om": 0.675, 
    "e": 0.751, 
    "i": 7.04, 
    "q": 0.2556, 
    "w": 137.58
  }, 
  {
    "a": 1.14, 
    "om": 0.696, 
    "e": 0.774, 
    "i": 6.6, 
    "q": 0.2577, 
    "w": 134.7
  }, 
  {
    "a": 1.153, 
    "om": 1.594, 
    "e": 0.785, 
    "i": 8.56, 
    "q": 0.2484, 
    "w": 135.34
  }, 
  {
    "a": 1.242, 
    "om": 1.606, 
    "e": 0.794, 
    "i": 8.27, 
    "q": 0.2562, 
    "w": 133.05
  }, 
  {
    "a": 1.002, 
    "om": 2.428, 
    "e": 0.777, 
    "i": 7.89, 
    "q": 0.2232, 
    "w": 141.05
  }, 
  {
    "a": 1.015, 
    "om": 2.501, 
    "e": 0.785, 
    "i": 8.84, 
    "q": 0.2182, 
    "w": 141.18
  }, 
  {
    "a": 1.098, 
    "om": 2.556, 
    "e": 0.781, 
    "i": 4.38, 
    "q": 0.2409, 
    "w": 137.15
  }, 
  {
    "a": 1.056, 
    "om": 2.673, 
    "e": 0.762, 
    "i": 4.67, 
    "q": 0.2517, 
    "w": 137.1
  }, 
  {
    "a": 0.969, 
    "om": 4.628, 
    "e": 0.732, 
    "i": 5.72, 
    "q": 0.2598, 
    "w": 138.84
  }
]